aries_community/__init__.py
aries_community/admin.py
aries_community/agent_utils.py
aries_community/apps.py
aries_community/forms.py
aries_community/indy_utils.py
aries_community/models.py
aries_community/registration_utils.py
aries_community/signals.py
aries_community/urls.py
aries_community/utils.py
aries_community/views.py
aries_community/wallet_utils.py
aries_community/management/__init__.py
aries_community/management/commands/__init__.py
aries_community/management/commands/loads_orgs.py
aries_community/management/commands/loads_schemas.py
aries_community/migrations/0001_initial.py
aries_community/migrations/0002_auto_20200301_1443.py
aries_community/migrations/0003_agentconversation_status.py
aries_community/migrations/__init__.py
aries_community/templates/.DS_Store
aries_community/templates/base_landing.html
aries_community/templates/base_nav.html
aries_community/templates/aries/.DS_Store
aries_community/templates/aries/base_individual_profile.html
aries_community/templates/aries/base_organization_profile.html
aries_community/templates/aries/data.html
aries_community/templates/aries/form_response.html
aries_community/templates/aries/profile.html
aries_community/templates/aries/wallet.html
aries_community/templates/aries/connection/.DS_Store
aries_community/templates/aries/connection/check_messages.html
aries_community/templates/aries/connection/form_connection_info.html
aries_community/templates/aries/connection/list.html
aries_community/templates/aries/connection/request.html
aries_community/templates/aries/connection/response.html
aries_community/templates/aries/connection/status.html
aries_community/templates/aries/conversation/.DS_Store
aries_community/templates/aries/conversation/list.html
aries_community/templates/aries/conversation/status.html
aries_community/templates/aries/credential/list.html
aries_community/templates/aries/credential/offer.html
aries_community/templates/aries/credential/offer_response.html
django_aries_community-0.1.3.dist-info/LICENSE
django_aries_community-0.1.3.dist-info/METADATA
django_aries_community-0.1.3.dist-info/WHEEL
django_aries_community-0.1.3.dist-info/top_level.txt
django_aries_community-0.1.3.dist-info/RECORD
